vectorlab/__init__.py
vectorlab/base.py
vectorlab/data/__init__.py
vectorlab/data/_argument_generator.py
vectorlab/data/_data_generator.py
vectorlab/data/dataloader/__init__.py
vectorlab/data/dataloader/_torch_dataloader.py
vectorlab/data/dataloader/_torch_geometric_dataloader.py
vectorlab/data/dataloader/tests/test_torch_dataloader.py
vectorlab/data/dataset/__init__.py
vectorlab/data/dataset/_torch_dataset.py
vectorlab/data/dataset/_ts_dataset.py
vectorlab/data/tests/test_argument_generator.py
vectorlab/data/tests/test_data_generator.py
vectorlab/ensemble/__init__.py
vectorlab/ensemble/_voting.py
vectorlab/ensemble/tests/test_ensemble_voting.py
vectorlab/graph/__init__.py
vectorlab/graph/_generator.py
vectorlab/graph/_utils.py
vectorlab/graph/tests/test_graph_generator.py
vectorlab/graph/tests/test_graph_utils.py
vectorlab/graph/walking/__init__.py
vectorlab/graph/walking/_bfs.py
vectorlab/graph/walking/_dfs.py
vectorlab/graph/walking/_random_walk.py
vectorlab/graph/walking/tests/test_graph_walking.py
vectorlab/metrics/__init__.py
vectorlab/metrics/pairwise/__init__.py
vectorlab/metrics/pairwise/_dtw.py
vectorlab/metrics/pairwise/_kl_div.py
vectorlab/metrics/pairwise/_lp_norm.py
vectorlab/metrics/pairwise/_sbd.py
vectorlab/metrics/pairwise/tests/test_metrics_pairwise.py
vectorlab/nn/__init__.py
vectorlab/nn/_earlystopping.py
vectorlab/nn/_logger.py
vectorlab/nn/_resolver.py
vectorlab/nn/explorer.py
vectorlab/nn/functional.py
vectorlab/nn/models/__init__.py
vectorlab/nn/models/_autoencoder.py
vectorlab/nn/models/_basic_gnn.py
vectorlab/nn/models/_classifier.py
vectorlab/nn/models/_decoder.py
vectorlab/nn/models/_encoder.py
vectorlab/nn/models/_gnn_decoder.py
vectorlab/nn/models/_mlp.py
vectorlab/nn/models/_seq2seq.py
vectorlab/nn/models/tests/test_decoder.py
vectorlab/nn/models/tests/test_encoder.py
vectorlab/nn/models/tests/test_seq2seq.py
vectorlab/nn/modules/__init__.py
vectorlab/nn/modules/gnn_loss.py
vectorlab/nn/modules/loss.py
vectorlab-1.0.3.dist-info/LICENSE.txt
vectorlab-1.0.3.dist-info/WHEEL
vectorlab-1.0.3.dist-info/METADATA
vectorlab-1.0.3.dist-info/RECORD
