Metadata-Version: 2.1
Name: vectorlab
Version: 1.0.3
Summary: A lab for vectors.
Author-email: Kyle Yang <kyle.yang1995@gmail.com>, Emma Qin <emmaqin0722@gmail.com>
Requires-Python: >=3.8
Classifier: Development Status :: 3 - Alpha
Classifier: License :: OSI Approved :: BSD License
Classifier: Programming Language :: Python :: 3.8
Classifier: Programming Language :: Python :: 3.9
Classifier: Programming Language :: Python :: 3.10
Classifier: Operating System :: OS Independent
Requires-Dist: numpy>=1.23.2
Requires-Dist: scipy>=1.9.0
Requires-Dist: pandas>=1.4.3
Requires-Dist: networkx>=2.8.6
Requires-Dist: statsmodels>=0.13.2
Requires-Dist: scikit-learn>=1.1.2
Requires-Dist: matplotlib>=3.5.3
Requires-Dist: seaborn>=0.11.2
Requires-Dist: pillow>=9.2.0
Requires-Dist: pytz>=2022.2.1
Requires-Dist: dill>=0.3.5.1
Requires-Dist: halo>=0.0.31
Requires-Dist: pyyaml>=6.0
Requires-Dist: wandb>=0.15.0
Requires-Dist: torchinfo>=1.6.3
Requires-Dist: tensorboard>=2.6.0
Requires-Dist: evaluate==0.4.0
Requires-Dist: accelerate>=0.18.0
Requires-Dist: torch>=1.10.0 ; extra == "full"
Requires-Dist: torch-sparse>=0.6.12 ; extra == "full"
Requires-Dist: torch-cluster>=1.6.0 ; extra == "full"
Requires-Dist: torch-scatter>=2.0.9 ; extra == "full"
Requires-Dist: torch-spline-conv>=1.2.1 ; extra == "full"
Requires-Dist: torch-geometric>=2.0.4 ; extra == "full"
Requires-Dist: pytest>=7.1.2 ; extra == "test"
Requires-Dist: pytest-cov>=3.0.0 ; extra == "test"
Requires-Dist: pytest-repeat>=0.9.1 ; extra == "test"
Requires-Dist: pytest-benchmark>=3.4.1 ; extra == "test"
Provides-Extra: full
Provides-Extra: test
